belfry_magicbell/__init__.py
belfry_magicbell/_version.py
belfry_magicbell/api/__init__.py
belfry_magicbell/api/_base.py
belfry_magicbell/api/_parsing.py
belfry_magicbell/api/channels.py
belfry_magicbell/api/graphql.py
belfry_magicbell/api/project.py
belfry_magicbell/api/push_subscription.py
belfry_magicbell/api/realtime.py
belfry_magicbell/api/user.py
belfry_magicbell/client.py
belfry_magicbell/configuration.py
belfry_magicbell/errors.py
belfry_magicbell/model/__init__.py
belfry_magicbell/model/_base.py
belfry_magicbell/model/channels.py
belfry_magicbell/model/notification.py
belfry_magicbell/model/project.py
belfry_magicbell/model/push_subscription.py
belfry_magicbell/model/response.py
belfry_magicbell/model/user.py
belfry_magicbell/model/workspace.py
belfry_magicbell-2.3.4.dist-info/LICENSE
belfry_magicbell-2.3.4.dist-info/METADATA
belfry_magicbell-2.3.4.dist-info/WHEEL
belfry_magicbell-2.3.4.dist-info/RECORD
