Metadata-Version: 2.3
Name: belfry_magicbell
Version: 2.3.4
Summary: Fork of the unofficial Python SDK for MagicBell
License: MIT
Keywords: magicbell,sdk
Author: Alex Tulenko
Author-email: alex@belfrysoftware.com
Requires-Python: >=3.8,<4.0
Classifier: License :: OSI Approved :: MIT License
Classifier: Programming Language :: Python :: 3
Classifier: Programming Language :: Python :: 3.8
Classifier: Programming Language :: Python :: 3.9
Classifier: Programming Language :: Python :: 3.10
Classifier: Programming Language :: Python :: 3.11
Classifier: Programming Language :: Python :: 3.12
Classifier: Programming Language :: Python :: 3.13
Requires-Dist: httpx (>=0.28.1)
Requires-Dist: orjson (>=3.7.6,<4.0.0)
Requires-Dist: pydantic (>=2.6,<3.0)
Requires-Dist: pydantic-settings (>=2.0.2,<3.0.0)
Project-URL: Repository, https://github.com/BelfrySoftware/magicbell-python-sdk
